MANIFEST.in
README.md
VERSION
setup.py
onos_api.egg-info/PKG-INFO
onos_api.egg-info/SOURCES.txt
onos_api.egg-info/dependency_links.txt
onos_api.egg-info/requires.txt
onos_api.egg-info/top_level.txt
python/gnmi/__init__.py
python/gnmi_ext/__init__.py
python/gogoproto/__init__.py
python/onos/__init__.py
python/onos/py.typed
python/onos/a1t/__init__.py
python/onos/a1t/a1/__init__.py
python/onos/a1t/admin/__init__.py
python/onos/config/__init__.py
python/onos/config/admin/__init__.py
python/onos/config/v2/__init__.py
python/onos/discovery/__init__.py
python/onos/e2t/__init__.py
python/onos/e2t/admin/__init__.py
python/onos/e2t/e2/__init__.py
python/onos/e2t/e2/v1beta1/__init__.py
python/onos/fabricsim/__init__.py
python/onos/kpimon/__init__.py
python/onos/mho/__init__.py
python/onos/misc/__init__.py
python/onos/mlb/__init__.py
python/onos/o1t/__init__.py
python/onos/p4rt/__init__.py
python/onos/pci/__init__.py
python/onos/perf/__init__.py
python/onos/provisioner/__init__.py
python/onos/ransim/__init__.py
python/onos/ransim/metrics/__init__.py
python/onos/ransim/model/__init__.py
python/onos/ransim/trafficsim/__init__.py
python/onos/ransim/types/__init__.py
python/onos/rsm/__init__.py
python/onos/topo/__init__.py
python/onos/uenib/__init__.py
python/p4/__init__.py
python/p4/config/__init__.py
python/stratum/__init__.py