Metadata-Version: 2.1
Name: onos-api
Version: 0.10.28
Summary: ONOS Python API
Home-page: https://github.com/onosproject/onos-api/
Author: Open Networking Foundation (ONF) and Partners
Author-email: support@opennetworking.org
License: Apache License v2.0
Download-URL: https://github.com/onosproject/onos-api/
Keywords: onos-api,python,protobuf,gnmi
Platform: UNKNOWN
Classifier: Development Status :: 4 - Beta
Classifier: Environment :: Other Environment
Classifier: Intended Audience :: Developers
Classifier: Operating System :: OS Independent
Classifier: Programming Language :: Python
Classifier: Programming Language :: Python :: 3
Classifier: Topic :: Utilities
Classifier: License :: OSI Approved :: Apache Software License
Classifier: Typing :: Typed
Requires-Python: >=3.6
